MANIFEST.in
README.txt
ez_setup.py
setup.py
locknix/__init__.py
locknix/lockfile.py
locknix.egg-info/PKG-INFO
locknix.egg-info/SOURCES.txt
locknix.egg-info/dependency_links.txt
locknix.egg-info/top_level.txt