Metadata-Version: 1.0
Name: locknix
Version: 1.0.3
Summary: NFS-safe file locking with timeouts for POSIX systems.
Home-page: https://launchpad.net/locknix
Author: Barry Warsaw
Author-email: barry@python.org
License: LGPL
Keywords: locking
Platform: UNKNOWN
